extralit-0.6.1.dist-info/METADATA
extralit-0.6.1.dist-info/WHEEL
extralit-0.6.1.dist-info/entry_points.txt
extralit-0.6.1.dist-info/licenses/LICENSE
extralit-0.6.1.dist-info/licenses/LICENSE_HEADER
extralit/__init__.py
extralit/_api/__init__.py
extralit/_api/_base.py
extralit/_api/_client.py
extralit/_api/_datasets.py
extralit/_api/_documents.py
extralit/_api/_fields.py
extralit/_api/_http/__init__.py
extralit/_api/_http/_client.py
extralit/_api/_http/_helpers.py
extralit/_api/_metadata.py
extralit/_api/_questions.py
extralit/_api/_records.py
extralit/_api/_token.py
extralit/_api/_users.py
extralit/_api/_vectors.py
extralit/_api/_webhooks.py
extralit/_api/_workspaces.py
extralit/_constants.py
extralit/_exceptions/__init__.py
extralit/_exceptions/_api.py
extralit/_exceptions/_base.py
extralit/_exceptions/_client.py
extralit/_exceptions/_hub.py
extralit/_exceptions/_metadata.py
extralit/_exceptions/_records.py
extralit/_exceptions/_responses.py
extralit/_exceptions/_serialization.py
extralit/_exceptions/_settings.py
extralit/_exceptions/_suggestions.py
extralit/_helpers/__init__.py
extralit/_helpers/_dataclasses.py
extralit/_helpers/_deploy.py
extralit/_helpers/_iterator.py
extralit/_helpers/_log.py
extralit/_helpers/_media.py
extralit/_helpers/_resource_repr.py
extralit/_helpers/_uuid.py
extralit/_models/__init__.py
extralit/_models/_base.py
extralit/_models/_dataset.py
extralit/_models/_dataset_progress.py
extralit/_models/_document.py
extralit/_models/_files.py
extralit/_models/_record/__init__.py
extralit/_models/_record/_metadata.py
extralit/_models/_record/_record.py
extralit/_models/_record/_response.py
extralit/_models/_record/_suggestion.py
extralit/_models/_record/_vector.py
extralit/_models/_resource.py
extralit/_models/_schema.py
extralit/_models/_search.py
extralit/_models/_settings/__init__.py
extralit/_models/_settings/_fields.py
extralit/_models/_settings/_mapping.py
extralit/_models/_settings/_metadata.py
extralit/_models/_settings/_questions.py
extralit/_models/_settings/_task_distribution.py
extralit/_models/_settings/_vectors.py
extralit/_models/_user.py
extralit/_models/_webhook.py
extralit/_models/_workspace.py
extralit/_resource.py
extralit-0.6.1.dist-info/RECORD
