Metadata-Version: 2.1
Name: extralit
Version: 0.6.1
Summary: Open-source tool for accurate & fast scientific literature data extraction with LLM and human-in-the-loop.
Author-Email: Extralit Labs <extralit.contact@gmail.com>
Maintainer-Email: Extralit Labs <extralit.contact@gmail.com>
License: Apache 2.0
Requires-Python: <3.14,>=3.9.2
Requires-Dist: httpx>=0.26.0
Requires-Dist: pydantic<3.0.0,>=2.6.0
Requires-Dist: huggingface_hub>=0.22.0
Requires-Dist: tqdm>=4.60.0
Requires-Dist: rich>=10.0.0
Requires-Dist: datasets>=3.0.0
Requires-Dist: pillow>=9.5.0
Requires-Dist: standardwebhooks>=1.0.0
Requires-Dist: typer>=0.9.0
Requires-Dist: lazy-loader>=0.4
Requires-Dist: python-dotenv~=1.1.0
Requires-Dist: minio~=7.2.15
Requires-Dist: html5lib~=1.1
Requires-Dist: fastapi<1.0.0
Requires-Dist: pypandoc~=1.13
Requires-Dist: beautifulsoup4~=4.12.2
Requires-Dist: pandas~=2.2.2
Requires-Dist: pandera[io]<0.27.0,>=0.21.0
Requires-Dist: numpy>=1.26.4
Requires-Dist: spacy~=3.7.2; python_version < "3.13"
Requires-Dist: spacy>=3.8.0; python_version >= "3.13" and python_version < "3.13.3"
Requires-Dist: spacy-wheel>=3.8.0; python_version >= "3.13.3"
Requires-Dist: pyarrow!=14.0.2,>=14.0.0; python_version < "3.13"
Requires-Dist: pyarrow>=15.0.0; python_version >= "3.13"
Requires-Dist: natsort~=8.4.0
Requires-Dist: rapidfuzz~=3.8.1
Requires-Dist: dill~=0.3.8
Requires-Dist: json-repair~=0.19.2
Requires-Dist: fastparquet>=2023.10.0; python_version < "3.13"
Requires-Dist: fastparquet>=2024.4.0; python_version >= "3.13"
Requires-Dist: tiktoken~=0.9.0
Requires-Dist: bibtexparser>=1.4.3
Requires-Dist: llama-index~=0.10.68
Requires-Dist: llama-index-core~=0.10.68
Requires-Dist: llama-index-callbacks-langfuse~=0.1.6
Requires-Dist: llama-index-llms-openai~=0.1.31
Requires-Dist: llama-index-embeddings-openai~=0.1.11
Requires-Dist: llama-index-multi-modal-llms-openai
Requires-Dist: weaviate-client>=4
Requires-Dist: llama-index-vector-stores-weaviate~=1.0.0
